README.rst
setup.cfg
setup.py
jupyter_qtconsole_colorschemes/__init__.py
jupyter_qtconsole_colorschemes/base16_ocean_dark.css
jupyter_qtconsole_colorschemes/base16_ocean_dark.py
jupyter_qtconsole_colorschemes/blackboard.css
jupyter_qtconsole_colorschemes/blackboard.py
jupyter_qtconsole_colorschemes/material_light.css
jupyter_qtconsole_colorschemes/material_light.py
jupyter_qtconsole_colorschemes/monokai.css
jupyter_qtconsole_colorschemes/solarizeddark.css
jupyter_qtconsole_colorschemes/solarizeddark.py
jupyter_qtconsole_colorschemes/solarizedlight.css
jupyter_qtconsole_colorschemes/solarizedlight.py
jupyter_qtconsole_colorschemes/spacemacs_dark.css
jupyter_qtconsole_colorschemes/spacemacs_dark.py
jupyter_qtconsole_colorschemes/tomorrow.css
jupyter_qtconsole_colorschemes/tomorrow.py
jupyter_qtconsole_colorschemes/zenburn.css
jupyter_qtconsole_colorschemes/zenburn.py
jupyter_qtconsole_colorschemes.egg-info/PKG-INFO
jupyter_qtconsole_colorschemes.egg-info/SOURCES.txt
jupyter_qtconsole_colorschemes.egg-info/dependency_links.txt
jupyter_qtconsole_colorschemes.egg-info/entry_points.txt
jupyter_qtconsole_colorschemes.egg-info/pbr.json
jupyter_qtconsole_colorschemes.egg-info/top_level.txt