Metadata-Version: 1.1
Name: jupyter-qtconsole-colorschemes
Version: 0.8.1
Summary: Color Schemes for Jupyter Qt Console
Home-page: https://bitbucket.org/joon/color-schemes-for-jupyter-qt-console
Author: Joon Ro
Author-email: joon.ro@outlook.com
License: UNKNOWN
Download-URL: https://bitbucket.org/joon/color-schemes-for-jupyter-qt-console/get/v0.8.1.zip
Platform: UNKNOWN
